INSTALL
MANIFEST.in
README.md
license.txt
setup.py
BGWpy/__init__.py
BGWpy/__main__.py
BGWpy.egg-info/PKG-INFO
BGWpy.egg-info/SOURCES.txt
BGWpy.egg-info/dependency_links.txt
BGWpy.egg-info/requires.txt
BGWpy.egg-info/top_level.txt
BGWpy/Abinit/__init__.py
BGWpy/Abinit/abibgw.py
BGWpy/Abinit/abidata.py
BGWpy/Abinit/abinitbgwflow.py
BGWpy/Abinit/abinitinput.py
BGWpy/Abinit/abinittask.py
BGWpy/Abinit/constructor.py
BGWpy/Abinit/scftask.py
BGWpy/Abinit/utils.py
BGWpy/Abinit/variable.py
BGWpy/Abinit/wfntask.py
BGWpy/BGW/__init__.py
BGWpy/BGW/absorptiontask.py
BGWpy/BGW/bgwtask.py
BGWpy/BGW/epsilontask.py
BGWpy/BGW/inputs.py
BGWpy/BGW/inteqptask.py
BGWpy/BGW/kerneltask.py
BGWpy/BGW/kgrid.py
BGWpy/BGW/sigmatask.py
BGWpy/BGW/vmtxeltask.py
BGWpy/DFT/__init__.py
BGWpy/DFT/dfttask.py
BGWpy/DFT/flows.py
BGWpy/DFT/wfnbgwflow.py
BGWpy/DFT/wfntask.py
BGWpy/QE/__init__.py
BGWpy/QE/constructor.py
BGWpy/QE/pwscfinput.py
BGWpy/QE/qebgwflow.py
BGWpy/QE/qebgwtask.py
BGWpy/QE/qetask.py
BGWpy/QE/scftask.py
BGWpy/QE/wfntask.py
BGWpy/Wannier90/__init__.py
BGWpy/Wannier90/pw2wan.py
BGWpy/Wannier90/sig2wan.py
BGWpy/Wannier90/wannier90.py
BGWpy/config/__init__.py
BGWpy/config/default_configuration.py
BGWpy/config/dft_flavors.py
BGWpy/core/F90io.py
BGWpy/core/__init__.py
BGWpy/core/runscript.py
BGWpy/core/task.py
BGWpy/core/util.py
BGWpy/core/workflow.py
BGWpy/core/writable.py
BGWpy/core/tests/__init__.py
BGWpy/core/tests/test_mpitask.py
BGWpy/core/tests/test_task.py
BGWpy/core/tests/test_writable.py
BGWpy/data/__init__.py
BGWpy/data/pseudos/14-Si.pspnc
BGWpy/data/pseudos/31-Ga.PBE.UPF
BGWpy/data/pseudos/33-As.PBE.UPF
BGWpy/data/pseudos/Si.UPF
BGWpy/data/pseudos/__init__.py
BGWpy/data/structures/GaAs.cif
BGWpy/data/structures/GaAs.json
BGWpy/data/structures/Si.cif
BGWpy/data/structures/Si.json
BGWpy/data/structures/__init__.py
BGWpy/data/structures/write-GaAs-structure.py
BGWpy/data/structures/write-Si-structure.py
BGWpy/external/__init__.py
BGWpy/external/xmltodict.py
BGWpy/extractors/__init__.py
BGWpy/extractors/eigenvalues.py
BGWpy/extractors/gw.py
BGWpy/extractors/inteqp.py
BGWpy/flows/__init__.py
BGWpy/flows/bseflow.py
