Metadata-Version: 2.1
Name: BGWpy
Version: 3.2.2
Summary: Interface BerkeleyGW flows in python.
Home-page: https://github.com/BerkeleyGW/BGWpy
Author: Gabriel Antonius
Author-email: gabriel.antonius@gmail.com
License: BSD
Platform: UNKNOWN
